envnx/__init__.py
envnx/cli.py
envnx/code_search.py
envnx/config_sync.py
envnx/env_check.py
envnx/proj_clean.py
envnx_cli-0.1.0.dist-info/METADATA
envnx_cli-0.1.0.dist-info/WHEEL
envnx_cli-0.1.0.dist-info/entry_points.txt
envnx_cli-0.1.0.dist-info/top_level.txt
envnx_cli-0.1.0.dist-info/RECORD
