Metadata-Version: 2.4
Name: envnx-cli
Version: 0.1.0
Summary: EnvNX – a small CLI toolkit for environment checks, project cleanup, code search, and config sync.
Author-email: Your Name <you@example.com>
Requires-Python: >=3.9
